firestore_batch/__init__.py
firestore_batch-0.0.1.dist-info/LICENSE
firestore_batch-0.0.1.dist-info/METADATA
firestore_batch-0.0.1.dist-info/WHEEL
firestore_batch-0.0.1.dist-info/top_level.txt
firestore_batch-0.0.1.dist-info/RECORD
