Metadata-Version: 2.1
Name: firestore-batch
Version: 0.0.1
Summary: A simple Python context manager for easy Google Forestore batched writes.
Home-page: https://github.com/leshchenko1979/firestore-batch
Author: Alexey Leshchenko
Author-email: leshchenko@gmail.com
License: MIT
Platform: UNKNOWN
Classifier: Programming Language :: Python :: 3
Classifier: License :: OSI Approved :: MIT License
Classifier: Operating System :: OS Independent
Requires-Python: >=3.6
